clustering_mi/__init__.py
clustering_mi/_input_output.py
clustering_mi/_util.py
clustering_mi/_version.py
clustering_mi/_version.pyi
clustering_mi/mutual_information.py
clustering_mi/py.typed
clustering_mi-0.1.6.dist-info/METADATA
clustering_mi-0.1.6.dist-info/WHEEL
clustering_mi-0.1.6.dist-info/licenses/LICENSE
clustering_mi-0.1.6.dist-info/RECORD
