Metadata-Version: 2.4
Name: clustering-mi
Version: 0.1.6
Summary: Compute the mutual information between two clusterings of the same objects
Project-URL: Homepage, https://github.com/maxjerdee/clustering-mi
Project-URL: Bug Tracker, https://github.com/maxjerdee/clustering-mi/issues
Project-URL: Discussions, https://github.com/maxjerdee/clustering-mi/discussions
Project-URL: Changelog, https://github.com/maxjerdee/clustering-mi/releases
Author-email: Max Jerdee <mjerdee@umich.edu>
License-Expression: MIT
License-File: LICENSE
Classifier: Development Status :: 1 - Planning
Classifier: Intended Audience :: Developers
Classifier: Intended Audience :: Science/Research
Classifier: Operating System :: OS Independent
Classifier: Programming Language :: Python
Classifier: Programming Language :: Python :: 3
Classifier: Programming Language :: Python :: 3 :: Only
Classifier: Programming Language :: Python :: 3.9
Classifier: Programming Language :: Python :: 3.10
Classifier: Programming Language :: Python :: 3.11
Classifier: Programming Language :: Python :: 3.12
Classifier: Programming Language :: Python :: 3.13
Classifier: Topic :: Scientific/Engineering
Classifier: Typing :: Typed
Requires-Python: >=3.9
Requires-Dist: numpy>=2.0.2
